lsdviztools/__init__.py
lsdviztools/cli.py
lsdviztools/lsdbasemaptools/__init__.py
lsdviztools/lsdbasemaptools/lsdmap_basemaptools.py
lsdviztools/lsdbasemaptools/lsdmap_hbdemdownloader.py
lsdviztools/lsdbasemaptools/lsdmap_otgrabber.py
lsdviztools/lsdmapfigure/__init__.py
lsdviztools/lsdmapfigure/plottinghelpers.py
lsdviztools/lsdmapfigure/plottingraster.py
lsdviztools/lsdmapwrappers/__init__.py
lsdviztools/lsdmapwrappers/lsdmapwrappers_basicplotting.py
lsdviztools/lsdmapwrappers/lsdmapwrappers_chiplotting.py
lsdviztools/lsdmapwrappers/lsdmapwrappers_lsdttcli.py
lsdviztools/lsdplottingtools/__init__.py
lsdviztools/lsdplottingtools/adjust_text.py
lsdviztools/lsdplottingtools/colours.py
lsdviztools/lsdplottingtools/cubehelix.py
lsdviztools/lsdplottingtools/dimension.py
lsdviztools/lsdplottingtools/inundation.py
lsdviztools/lsdplottingtools/joyplot.py
lsdviztools/lsdplottingtools/labels.py
lsdviztools/lsdplottingtools/locationmap.py
lsdviztools/lsdplottingtools/lsdmap_basicmanipulation.py
lsdviztools/lsdplottingtools/lsdmap_basicmaps.py
lsdviztools/lsdplottingtools/lsdmap_basicplotting.py
lsdviztools/lsdplottingtools/lsdmap_chiplotting.py
lsdviztools/lsdplottingtools/lsdmap_drainagecapture.py
lsdviztools/lsdplottingtools/lsdmap_gdalio.py
lsdviztools/lsdplottingtools/lsdmap_hillslopemorphology.py
lsdviztools/lsdplottingtools/lsdmap_knickpointplotting.py
lsdviztools/lsdplottingtools/lsdmap_lithoplotting.py
lsdviztools/lsdplottingtools/lsdmap_movernplotting.py
lsdviztools/lsdplottingtools/lsdmap_osystemtools.py
lsdviztools/lsdplottingtools/lsdmap_plottingdriver.py
lsdviztools/lsdplottingtools/lsdmap_pointtools.py
lsdviztools/lsdplottingtools/lsdmap_saplotting.py
lsdviztools/lsdplottingtools/lsdmap_subplots.py
lsdviztools/lsdplottingtools/lsdmap_swathplotting.py
lsdviztools/lsdplottingtools/lsdmap_terraceplotting.py
lsdviztools/lsdplottingtools/lsdmap_vectortools.py
lsdviztools/lsdplottingtools/scalebar.py
lsdviztools/lsdplottingtools/setup_cython.py
lsdviztools-0.4.15.dist-info/AUTHORS.rst
lsdviztools-0.4.15.dist-info/LICENSE.txt
lsdviztools-0.4.15.dist-info/METADATA
lsdviztools-0.4.15.dist-info/WHEEL
lsdviztools-0.4.15.dist-info/entry_points.txt
lsdviztools-0.4.15.dist-info/top_level.txt
lsdviztools-0.4.15.dist-info/RECORD
