Metadata-Version: 2.1
Name: lsdviztools
Version: 0.4.15
Summary: lsdviztools is a collection of routines for plotting geospatial data, with a focus on data produces by LSDTopoTools or by lsdtopytools.
Home-page: https://github.com/LSDTopotools/lsdviztools
Author: Simon Marius Mudd
Author-email: simon.m.mudd@ed.ac.uk
License: MIT
Keywords: lsdviztools,lsdtopotools,lsdtopytools,GIS,topographic analysis,remote sensing,geomorphology,earth observation
Classifier: Development Status :: 2 - Pre-Alpha
Classifier: Intended Audience :: Developers
Classifier: License :: OSI Approved :: MIT License
Classifier: Natural Language :: English
Classifier: Programming Language :: Python :: 3
Classifier: Programming Language :: Python :: 3.6
Classifier: Programming Language :: Python :: 3.7
Classifier: Programming Language :: Python :: 3.8
Classifier: Programming Language :: Python :: 3.9
Classifier: Programming Language :: Python :: 3.10
Classifier: Programming Language :: Python :: 3.11
Classifier: Programming Language :: Python :: 3.12
Requires-Python: >=3.6
License-File: LICENSE.txt
License-File: AUTHORS.rst
Requires-Dist: numpy
Requires-Dist: pandas
Requires-Dist: rasterio
Requires-Dist: scipy
Requires-Dist: cartopy
Requires-Dist: fiona
Requires-Dist: shapely
Requires-Dist: geopandas
Requires-Dist: pyproj
Requires-Dist: gdal
Requires-Dist: utm
Requires-Dist: matplotlib
